dbrd/__init__.py
dbrd/example.py
dbrd-0.0.1.dist-info/METADATA
dbrd-0.0.1.dist-info/WHEEL
dbrd-0.0.1.dist-info/top_level.txt
dbrd-0.0.1.dist-info/RECORD
